MANIFEST.in
README.md
setup.py
data/dw961.wav
data/lsen1.wav
kaldiasr/__init__.py
kaldiasr/gmm.pyx
kaldiasr/gmm_wrappers.cpp
kaldiasr/gmm_wrappers.h
kaldiasr/nnet3.pyx
kaldiasr/nnet3_wrappers.cpp
kaldiasr/nnet3_wrappers.h
py_kaldi_asr.egg-info/PKG-INFO
py_kaldi_asr.egg-info/SOURCES.txt
py_kaldi_asr.egg-info/dependency_links.txt
py_kaldi_asr.egg-info/requires.txt
py_kaldi_asr.egg-info/top_level.txt