Metadata-Version: 1.1
Name: py-kaldi-asr
Version: 0.5.2
Summary: Simple Python/Cython interface to kaldi-asr nnet3/chain and gmm decoders
Home-page: https://github.com/gooofy/py-kaldi-asr
Author: Guenter Bartsch
Author-email: guenter@zamia.org
License: Apache
Keywords: kaldi asr
Platform: UNKNOWN
Classifier: Operating System :: POSIX :: Linux
Classifier: License :: OSI Approved :: Apache Software License
Classifier: Programming Language :: Python :: 2
Classifier: Programming Language :: Python :: 2.7
Classifier: Programming Language :: Python :: 3
Classifier: Programming Language :: Python :: 3.5
Classifier: Programming Language :: Cython
Classifier: Programming Language :: C++
Classifier: Intended Audience :: Developers
Classifier: Topic :: Software Development :: Libraries :: Python Modules
Classifier: Topic :: Multimedia :: Sound/Audio :: Speech
